xia_scw_vpc/__init__.py
xia_scw_vpc/vpc.cp310-win_amd64.pyd
xia_scw_vpc/templates/ScwVpc/main.tf
xia_scw_vpc/templates/ScwVpc/output.tf
xia_scw_vpc/templates/ScwVpc/provider.tf
xia_scw_vpc/templates/ScwVpc/variables.tf
xia_scw_vpc-0.1.4.dist-info/LICENSE.txt
xia_scw_vpc-0.1.4.dist-info/METADATA
xia_scw_vpc-0.1.4.dist-info/WHEEL
xia_scw_vpc-0.1.4.dist-info/top_level.txt
xia_scw_vpc-0.1.4.dist-info/RECORD
