Metadata-Version: 2.1
Name: xia-scw-vpc
Version: 0.1.4
Summary: X-I-A
Home-page: https://develop.x-i-a.com/docs/xia-scw-vpc/0.1.4/index.html
Author: X-I-A
Author-email: admin@x-i-a.com
License: UNKNOWN
Platform: UNKNOWN
Requires-Python: >=3.9
License-File: LICENSE.txt
Requires-Dist: xia-engine
Requires-Dist: xia-fields-scw
